grok3api/__init__.py
grok3api/client.py
grok3api/driver.py
grok3api/history.py
grok3api/logger.py
grok3api/server.py
grok3api/types/GeneratedImage.py
grok3api/types/GrokResponse.py
grok3api-0.1.0b7.dist-info/licenses/LICENSE
grok3api-0.1.0b7.dist-info/METADATA
grok3api-0.1.0b7.dist-info/WHEEL
grok3api-0.1.0b7.dist-info/top_level.txt
grok3api-0.1.0b7.dist-info/RECORD
