Metadata-Version: 2.4
Name: Grok3API
Version: 0.1.0b7
Summary: Python-библиотека для взаимодействия с Grok3, ориентированная на максимальную простоту использования. Автоматически получает cookies, поэтому ничего не нужно указывать. A Python library for interacting with Grok3, focused on maximum ease of use. Automatically gets cookies, so you don't have to specify anything.
Author-email: boykopovar <boykopovar@gmail.com>
License-Expression: MIT
Project-URL: Homepage, https://github.com/boykopovar/Grok3API
Keywords: grok3api,grok 3 api,grok api,grok3api python,grok ai,unofficial grok3api api
Classifier: Programming Language :: Python :: 3
Classifier: Operating System :: OS Independent
Requires-Python: >=3.8
License-File: LICENSE
Requires-Dist: undetected-chromedriver>=3.5.5
Dynamic: license-file
